wakapi_anyide-0.6.8.dist-info/METADATA
wakapi_anyide-0.6.8.dist-info/WHEEL
wakapi_anyide-0.6.8.dist-info/entry_points.txt
wakapi_anyide-0.6.8.dist-info/licenses/LICENSE
wakapi_anyide/models/project.py
wakapi_anyide/models/__init__.py
wakapi_anyide/models/environment.py
wakapi_anyide/models/config.py
wakapi_anyide/watchers/filewatcher.py
wakapi_anyide/watchers/__init__.py
wakapi_anyide/watchers/types.py
wakapi_anyide/_rust/watch/__init__.pyi
wakapi_anyide/_rust/__init__.pyi
wakapi_anyide/__init__.py
wakapi_anyide/runner.py
wakapi_anyide/__main__.py
wakapi_anyide/helpers/__init__.py
wakapi_anyide/helpers/ini.py
wakapi_anyide/helpers/filediffer.py
wakapi_anyide/py.typed
wakapi_anyide/_rust.abi3.so
wakapi_anyide-0.6.8.dist-info/RECORD
