Metadata-Version: 2.4
Name: wakapi-anyide
Version: 0.6.8
Classifier: Development Status :: 4 - Beta
Classifier: Environment :: Console
Classifier: Intended Audience :: Developers
Classifier: License :: Public Domain
Classifier: Programming Language :: Rust
Classifier: Programming Language :: Python :: 3.12
Classifier: Programming Language :: Python :: Implementation :: CPython
Requires-Dist: aiohttp ~=3.10.10
Requires-Dist: typer-slim ~=0.12.5
Requires-Dist: aiofiles ~=24.1.0
Requires-Dist: pydantic ~=2.9.2
Requires-Dist: pydantic-settings ~=2.6.1
Requires-Dist: pathspec ~=0.12.1
Requires-Dist: rich ~=13.9.4 ; extra == 'color'
Provides-Extra: color
License-File: LICENSE
Summary: Time tracking for any IDE with WakaTime-like servers
Author: Sarah C
Maintainer: Sarah C
Requires-Python: >=3.12
